README.rst
setup.py
jb_everything/__init__.py
jb_everything.egg-info/PKG-INFO
jb_everything.egg-info/SOURCES.txt
jb_everything.egg-info/dependency_links.txt
jb_everything.egg-info/requires.txt
jb_everything.egg-info/top_level.txt