Metadata-Version: 1.0
Name: jb-everything
Version: 0.1.0
Summary: Large list of imports for machine learning.
Home-page: https://pypi.org/project/jb-everything/
Author: jeromebaum
Author-email: jerome@jeromebaum.com
License: MIT
Platform: UNKNOWN
